AnsiList.py
ChorusFruit.py
__init__.py
setup.py
ChorusFruit_mani.f-0.0.1.dist-info/LICENCE
ChorusFruit_mani.f-0.0.1.dist-info/METADATA
ChorusFruit_mani.f-0.0.1.dist-info/WHEEL
ChorusFruit_mani.f-0.0.1.dist-info/top_level.txt
ChorusFruit_mani.f-0.0.1.dist-info/RECORD
